fastqtools/__init__.py
fastqtools/fastqReader/__init__.py
fastqtools/fastqReader/fastqReader.py
fastqtools/fastqReader/fastqWriter.py
fastqtools/fastqSplit/__init__.py
fastqtools/fastqSplit/fastqMerge.py
fastqtools/fastqSplit/fastqSplit.py
fastqtools/fastqSplit/getfileNum.py
fastqtools/fastqStat/__init__.py
fastqtools/fastqStat/fastqStat.py
fastqtools/fastqStat/getfileNum.py
fastqtools/readprocess/__init__.py
fastqtools/readprocess/readprocess.py
fastqtools/readprocess/tools.py
fastqtools-0.3.3.data/scripts/fastqClean.py
fastqtools-0.3.3.data/scripts/fastqSplit.py
fastqtools-0.3.3.data/scripts/fastqStat.py
fastqtools-0.3.3.dist-info/METADATA
fastqtools-0.3.3.dist-info/RECORD
fastqtools-0.3.3.dist-info/WHEEL
fastqtools-0.3.3.dist-info/top_level.txt
