Metadata-Version: 2.1
Name: fastqtools
Version: 0.3.3
Summary: Add a short description here!
Home-page: https://github.com/vienomics/fastqtools
Author: KongDeju
Author-email: kongdeju@vienomics.com
License: none
Platform: UNKNOWN
Classifier: Development Status :: 4 - Beta
Classifier: Programming Language :: Python
